{
  "kind": "youtube#searchListResponse",
  "etag": "4-G4GPi8llYb8fY-FMhb7EsszQQ",
  "nextPageToken": "CAUQAA",
  "regionCode": "BY",
  "pageInfo": {
    "totalResults": 154,
    "resultsPerPage": 5
  },
  "items": [
    {
      "kind": "youtube#searchResult",
      "etag": "vx7QMwKuqCz_cEGpIJpRJwhRirk",
      "id": {
        "kind": "youtube#video",
        "videoId": "OnRDo6Kg8LY"
      },
      "snippet": {
        "publishedAt": "2020-02-06T05:41:15Z",
        "channelId": "UCvuShrOlcCtLoJ7gEUwB0FA",
        "title": "Самое первое видео про SUBARU TEAM BELARUS (2015)",
        "description": "Да! Это самый первое смонтированное видео от нашего клуба и снято оно было в январе 2015-ого года. Пусть видео и не наивысшего качества, ...",
        "thumbnails": {
          "default": {
            "url": "https://i.ytimg.com/vi/OnRDo6Kg8LY/default.jpg",
            "width": 120,
            "height": 90
          },
          "medium": {
            "url": "https://i.ytimg.com/vi/OnRDo6Kg8LY/mqdefault.jpg",
            "width": 320,
            "height": 180
          },
          "high": {
            "url": "https://i.ytimg.com/vi/OnRDo6Kg8LY/hqdefault.jpg",
            "width": 480,
            "height": 360
          }
        },
        "channelTitle": "SUBARU TEAM BELARUS",
        "liveBroadcastContent": "none",
        "publishTime": "2020-02-06T05:41:15Z"
      }
    },
    {
      "kind": "youtube#searchResult",
      "etag": "cW7D_eZuws_sAq2yCiyHcdTr8u4",
      "id": {
        "kind": "youtube#video",
        "videoId": "OUqkAGRTeeo"
      },
      "snippet": {
        "publishedAt": "2021-03-30T12:17:58Z",
        "channelId": "UCI8ho-tis9HHe0jZvXjn68w",
        "title": "Subaru Team Belarus (gumkhana) Inst. @sco_o4",
        "description": "",
        "thumbnails": {
          "default": {
            "url": "https://i.ytimg.com/vi/OUqkAGRTeeo/default.jpg",
            "width": 120,
            "height": 90
          },
          "medium": {
            "url": "https://i.ytimg.com/vi/OUqkAGRTeeo/mqdefault.jpg",
            "width": 320,
            "height": 180
          },
          "high": {
            "url": "https://i.ytimg.com/vi/OUqkAGRTeeo/hqdefault.jpg",
            "width": 480,
            "height": 360
          }
        },
        "channelTitle": "sco4",
        "liveBroadcastContent": "none",
        "publishTime": "2021-03-30T12:17:58Z"
      }
    },
    {
      "kind": "youtube#searchResult",
      "etag": "HPCHFQXgsh1aKjm3jINoiZ30a4A",
      "id": {
        "kind": "youtube#video",
        "videoId": "okrdfDW6Fm0"
      },
      "snippet": {
        "publishedAt": "2019-03-02T11:08:53Z",
        "channelId": "UCadvFxUgfiPCG1rlOtM9sAg",
        "title": "Subaru Team Belarus",
        "description": "",
        "thumbnails": {
          "default": {
            "url": "https://i.ytimg.com/vi/okrdfDW6Fm0/default.jpg",
            "width": 120,
            "height": 90
          },
          "medium": {
            "url": "https://i.ytimg.com/vi/okrdfDW6Fm0/mqdefault.jpg",
            "width": 320,
            "height": 180
          },
          "high": {
            "url": "https://i.ytimg.com/vi/okrdfDW6Fm0/hqdefault.jpg",
            "width": 480,
            "height": 360
          }
        },
        "channelTitle": "Mr SpAwN",
        "liveBroadcastContent": "none",
        "publishTime": "2019-03-02T11:08:53Z"
      }
    },
    {
      "kind": "youtube#searchResult",
      "etag": "IVMYZQji9B-RWollLPxXPW2Zxd0",
      "id": {
        "kind": "youtube#video",
        "videoId": "20XdKM4FdI4"
      },
      "snippet": {
        "publishedAt": "2015-06-18T15:02:52Z",
        "channelId": "UCNXPO2WfBVd1kz6nvVrlvWQ",
        "title": "GOPRO Subaru team Belarus сралимынаваше rally =)",
        "description": "",
        "thumbnails": {
          "default": {
            "url": "https://i.ytimg.com/vi/20XdKM4FdI4/default.jpg",
            "width": 120,
            "height": 90
          },
          "medium": {
            "url": "https://i.ytimg.com/vi/20XdKM4FdI4/mqdefault.jpg",
            "width": 320,
            "height": 180
          },
          "high": {
            "url": "https://i.ytimg.com/vi/20XdKM4FdI4/hqdefault.jpg",
            "width": 480,
            "height": 360
          }
        },
        "channelTitle": "Рома Падунович",
        "liveBroadcastContent": "none",
        "publishTime": "2015-06-18T15:02:52Z"
      }
    },
    {
      "kind": "youtube#searchResult",
      "etag": "iuq1nH1gH6p7qCaDsjwW30NXoUw",
      "id": {
        "kind": "youtube#video",
        "videoId": "kPV1u-MJAXg"
      },
      "snippet": {
        "publishedAt": "2015-01-10T06:49:10Z",
        "channelId": "UC4eLHLoI4AvlA16YXIe_ROw",
        "title": "Subaru Team Belarus   02",
        "description": "09.01.2015.",
        "thumbnails": {
          "default": {
            "url": "https://i.ytimg.com/vi/kPV1u-MJAXg/default.jpg",
            "width": 120,
            "height": 90
          },
          "medium": {
            "url": "https://i.ytimg.com/vi/kPV1u-MJAXg/mqdefault.jpg",
            "width": 320,
            "height": 180
          },
          "high": {
            "url": "https://i.ytimg.com/vi/kPV1u-MJAXg/hqdefault.jpg",
            "width": 480,
            "height": 360
          }
        },
        "channelTitle": "Alexandr Urbanovich",
        "liveBroadcastContent": "none",
        "publishTime": "2015-01-10T06:49:10Z"
      }
    }
  ]
}
